bigdl/__init__.py
bigdl/llm/__init__.py
bigdl/llm/convert_model.py
bigdl/llm/models.py
bigdl/llm/optimize.py
bigdl/llm/cli/llm-chat
bigdl/llm/cli/llm-chat.ps1
bigdl/llm/cli/llm-cli
bigdl/llm/cli/llm-cli.ps1
bigdl/llm/cli/prompts/chat-with-llm.txt
bigdl/llm/ggml/__init__.py
bigdl/llm/ggml/convert.py
bigdl/llm/ggml/convert_model.py
bigdl/llm/ggml/quantize.py
bigdl/llm/ggml/model/__init__.py
bigdl/llm/ggml/model/bloom/__init__.py
bigdl/llm/ggml/model/bloom/bloom.py
bigdl/llm/ggml/model/bloom/bloom_cpp.py
bigdl/llm/ggml/model/chatglm/__init__.py
bigdl/llm/ggml/model/chatglm/chatglm.py
bigdl/llm/ggml/model/chatglm/chatglm_cpp.py
bigdl/llm/ggml/model/generation/__init__.py
bigdl/llm/ggml/model/generation/utils.py
bigdl/llm/ggml/model/gptneox/__init__.py
bigdl/llm/ggml/model/gptneox/gptneox.py
bigdl/llm/ggml/model/gptneox/gptneox_cpp.py
bigdl/llm/ggml/model/gptneox/gptneox_types.py
bigdl/llm/ggml/model/llama/__init__.py
bigdl/llm/ggml/model/llama/llama.py
bigdl/llm/ggml/model/llama/llama_cpp.py
bigdl/llm/ggml/model/llama/llama_types.py
bigdl/llm/ggml/model/starcoder/__init__.py
bigdl/llm/ggml/model/starcoder/starcoder.py
bigdl/llm/ggml/model/starcoder/starcoder_cpp.py
bigdl/llm/gptq/__init__.py
bigdl/llm/gptq/convert/__init__.py
bigdl/llm/gptq/convert/convert_gptq_to_ggml.py
bigdl/llm/langchain/__init__.py
bigdl/llm/langchain/embeddings/__init__.py
bigdl/llm/langchain/embeddings/bigdlllm.py
bigdl/llm/langchain/embeddings/transformersembeddings.py
bigdl/llm/langchain/llms/__init__.py
bigdl/llm/langchain/llms/bigdlllm.py
bigdl/llm/langchain/llms/transformersllm.py
bigdl/llm/langchain/llms/transformerspipelinellm.py
bigdl/llm/libs/__init__.py
bigdl/llm/libs/chatglm_C.cpython-310-x86_64-linux-gnu.so
bigdl/llm/libs/chatglm_C.cpython-311-x86_64-linux-gnu.so
bigdl/llm/libs/chatglm_C.cpython-39-x86_64-linux-gnu.so
bigdl/llm/libs/libbloom-api.so
bigdl/llm/libs/libbloom_amx.so
bigdl/llm/libs/libbloom_avx.so
bigdl/llm/libs/libbloom_avx2.so
bigdl/llm/libs/libbloom_avx512.so
bigdl_llm-2.4.0.dist-info/METADATA
bigdl_llm-2.4.0.dist-info/WHEEL
bigdl_llm-2.4.0.dist-info/entry_points.txt
bigdl_llm-2.4.0.dist-info/top_level.txt
bigdl_llm-2.4.0.dist-info/RECORD
