Metadata-Version: 2.1
Name: bigdl-llm
Version: 2.4.0
Summary: Large Language Model Develop Toolkit
Home-page: https://github.com/intel-analytics/BigDL
Author: BigDL Authors
Author-email: bigdl-user-group@googlegroups.com
License: Apache License, Version 2.0
Platform: windows
Classifier: License :: OSI Approved :: Apache Software License
Classifier: Programming Language :: Python :: 3
Classifier: Programming Language :: Python :: 3.9
Classifier: Programming Language :: Python :: Implementation :: CPython
Provides-Extra: all
Requires-Dist: py-cpuinfo ; extra == 'all'
Requires-Dist: protobuf ; extra == 'all'
Requires-Dist: numpy (>=1.22) ; extra == 'all'
Requires-Dist: torch ; extra == 'all'
Requires-Dist: transformers (==4.31.0) ; extra == 'all'
Requires-Dist: sentencepiece ; extra == 'all'
Requires-Dist: tokenizers (==0.13.3) ; extra == 'all'
Requires-Dist: accelerate (==0.21.0) ; extra == 'all'
Requires-Dist: tabulate ; extra == 'all'
Requires-Dist: intel-openmp ; (platform_machine == "x86_64" or platform_machine == "AMD64") and extra == 'all'
Provides-Extra: serving
Requires-Dist: py-cpuinfo ; extra == 'serving'
Requires-Dist: fschat[model_worker,webui] (==0.2.28) ; extra == 'serving'
Requires-Dist: protobuf ; extra == 'serving'
Provides-Extra: xpu
Requires-Dist: py-cpuinfo ; extra == 'xpu'
Requires-Dist: protobuf ; extra == 'xpu'
Requires-Dist: numpy (>=1.22) ; extra == 'xpu'
Requires-Dist: transformers (==4.31.0) ; extra == 'xpu'
Requires-Dist: sentencepiece ; extra == 'xpu'
Requires-Dist: tokenizers (==0.13.3) ; extra == 'xpu'
Requires-Dist: accelerate (==0.21.0) ; extra == 'xpu'
Requires-Dist: tabulate ; extra == 'xpu'
Requires-Dist: torch (==2.0.1a0) ; extra == 'xpu'
Requires-Dist: torchvision (==0.15.2a0) ; extra == 'xpu'
Requires-Dist: intel-openmp ; (platform_machine == "x86_64" or platform_machine == "AMD64") and extra == 'xpu'
Requires-Dist: intel-extension-for-pytorch (==2.0.110+xpu) ; (platform_system == "Linux") and extra == 'xpu'
Requires-Dist: bigdl-core-xe (==2.4.0) ; (platform_system == "Linux") and extra == 'xpu'
Requires-Dist: bigdl-core-xe-esimd (==2.4.0) ; (platform_system == "Linux") and extra == 'xpu'
